{
  "iprs": [
    {
      "id": 1,
      "IDNUMBER": "92850192",
      "FATHERNAMES": "JULIUS MUNENE KABIRO",
      "FULLNAMES": "ROSELLA BRADE CATTEMULL",
      "MOTHERNAMES": "IRENE LUKY MTODO",
      "SERIALNUMBER": "435278219",
      "GENDER": "M",
      "ADRESS": "",
      "DATEOFBIRTH": "1990/01/01",
      "DISTRICTOFBIRTH": "LAMU"
    },
    {
      "id": 2,
      "IDNUMBER": "82389890",
      "FATHERNAMES": "TOM ASIEGO KAMARA",
      "FULLNAMES": "GERY JENA MACCRANN",
      "MOTHERNAMES": "LUCY EROKO KOGO",
      "SERIALNUMBER": "67328839",
      "GENDER": "M",
      "ADRESS": "",
      "DATEOFBIRTH": "1983/08/06",
      "DISTRICTOFBIRTH": "KABURENGU"
    },
    {
      "id": 3,
      "IDNUMBER": "34567893",
      "FATHERNAMES": "IAN MTORO MTORO",
      "FULLNAMES": "HILDY FELISHA COURT",
      "MOTHERNAMES": "ISABELLA WAMBOI MTORO",
      "SERIALNUMBER": "54677832",
      "GENDER": "F",
      "ADRESS": "",
      "DATEOFBIRTH": "1958/04/08",
      "DISTRICTOFBIRTH": "BUKACHI"
    },
    {
      "id": 4,
      "IDNUMBER": "87356782",
      "FATHERNAMES": "STANLY OSORE OKIEK",
      "FULLNAMES": "ALI PAULE MCGUANE",
      "MOTHERNAMES": "MARY WANGOSI",
      "SERIALNUMBER": "43683283",
      "GENDER": "M",
      "ADRESS": "",
      "DATEOFBIRTH": "1960/12/05",
      "DISTRICTOFBIRTH": "MBALOZI"
    },
    {
      "id": 5,
      "IDNUMBER": "87356745",
      "FATHERNAMES": "KEVIN OSORE OKIEK",
      "FULLNAMES": "DAVID PAULE MCGUANE",
      "MOTHERNAMES": "CLAIRE WANGOSI",
      "SERIALNUMBER": "43683234",
      "GENDER": "M",
      "ADRESS": "",
      "DATEOFBIRTH": "1960/12/05",
      "DISTRICTOFBIRTH": "MBALOZI"
    },
    {
      "id": 6,
      "IDNUMBER": "87356731",
      "FATHERNAMES": "GEORGE OSORE OKIEK",
      "FULLNAMES": "PAUL PAULE MCGUANE",
      "MOTHERNAMES": "DAISY WANGOSI",
      "SERIALNUMBER": "43683266",
      "GENDER": "M",
      "ADRESS": "",
      "DATEOFBIRTH": "1960/12/05",
      "DISTRICTOFBIRTH": "MBALOZI"
    }
  ],
  "kra": [
    {
      "id": 1,
      "MIDDLENAME": "ROSELLA",
      "MPOBOX": "83931",
      "MTOWN": "HENGPI",
      "POCODE": null,
      "RTELNO": "0744934786",
      "STARTUPDATE": "2005/02/10",
      "TAXPAYERSPIN": "S978847009",
      "FISRTNAME": "BRADE",
      "LASTNAME": "CATTEMULL",
      "IDNUMBER": "92850192"
    },
    {
      "id": 2,
      "MIDDLENAME": "GERY",
      "MPOBOX": "0341",
      "MTOWN": "TLOGOSADANG",
      "POCODE": null,
      "RTELNO": "0753990486",
      "STARTUPDATE": "2003/03/27",
      "TAXPAYERSPIN": "G464410779",
      "FISRTNAME": "JENA",
      "LASTNAME": "MACCRANN",
      "IDNUMBER": "82389890"
    },
    {
      "id": 3,
      "MIDDLENAME": "HILDY",
      "MPOBOX": "118",
      "MTOWN": "SAINT-ÉTIENNE",
      "POCODE": "42045 CEDEX 1",
      "RTELNO": "0726096691",
      "STARTUPDATE": "2002/01/29",
      "TAXPAYERSPIN": "F853255186",
      "FISRTNAME": "FELISHA",
      "LASTNAME": "COURT",
      "IDNUMBER": "30277705"
    },
    {
      "id": 4,
      "MIDDLENAME": "ALI",
      "MPOBOX": "28718",
      "MTOWN": "DONGKENGKOU",
      "POCODE": null,
      "RTELNO": "0763456838",
      "STARTUPDATE": "2019/07/19",
      "TAXPAYERSPIN": "N582443084",
      "FISRTNAME": "PAULE",
      "LASTNAME": "MCGUANE",
      "IDNUMBER": "33789835"
    },
    {
      "id": 5,
      "MIDDLENAME": "WALLIW",
      "MPOBOX": "60007",
      "MTOWN": "HIKONE",
      "POCODE": "526-0826",
      "RTELNO": "0779824314",
      "STARTUPDATE": "2014/06/12",
      "TAXPAYERSPIN": "J717658343",
      "FISRTNAME": "JOSEFINA",
      "LASTNAME": "BOSCHMANN",
      "IDNUMBER": "50261315"
    },
    {
      "id": 6,
      "MIDDLENAME": "RING",
      "MPOBOX": "0611",
      "MTOWN": "VOSTOCHNYY",
      "POCODE": "612711",
      "RTELNO": "0771554586",
      "STARTUPDATE": "2016/10/25",
      "TAXPAYERSPIN": "A730078207",
      "FISRTNAME": "IRVIN",
      "LASTNAME": "ASTLES",
      "IDNUMBER": "68063083"
    },
    {
      "id": 7,
      "MIDDLENAME": "DUFF",
      "MPOBOX": "80",
      "MTOWN": "PASARBARU",
      "POCODE": null,
      "RTELNO": "0734643954",
      "STARTUPDATE": "2002/05/08",
      "TAXPAYERSPIN": "L979625799",
      "FISRTNAME": "BARRIE",
      "LASTNAME": "DUGDALE",
      "IDNUMBER": "19665958"
    },
    {
      "id": 8,
      "MIDDLENAME": "FRAN",
      "MPOBOX": "8",
      "MTOWN": "HUANGBEN",
      "POCODE": null,
      "RTELNO": "0796218031",
      "STARTUPDATE": "2018/04/19",
      "TAXPAYERSPIN": "F457016814",
      "FISRTNAME": "DESIREE",
      "LASTNAME": "GILBY",
      "IDNUMBER": "11316636"
    },
    {
      "id": 9,
      "MIDDLENAME": "BECK",
      "MPOBOX": "25",
      "MTOWN": "ANG THONG",
      "POCODE": "14000",
      "RTELNO": "0728834986",
      "STARTUPDATE": "2002/11/08",
      "TAXPAYERSPIN": "N291937642",
      "FISRTNAME": "AME",
      "LASTNAME": "BRUCKMANN",
      "IDNUMBER": "92232408"
    },
    {
      "id": 10,
      "MIDDLENAME": "MELICENT",
      "MPOBOX": "4856",
      "MTOWN": "SAN VICENTE PACAYA",
      "POCODE": "05012",
      "RTELNO": "0736735724",
      "STARTUPDATE": "2014/11/13",
      "TAXPAYERSPIN": "R654882919",
      "FISRTNAME": "KATHI",
      "LASTNAME": "STRETTELL",
      "IDNUMBER": "94029622"
    },
    {
      "id": 11,
      "MIDDLENAME": "BECK",
      "MPOBOX": "25",
      "MTOWN": "ANG THONG",
      "POCODE": "14000",
      "RTELNO": "0728834986",
      "STARTUPDATE": "2002/11/08",
      "TAXPAYERSPIN": "N291937642",
      "FISRTNAME": "AME",
      "LASTNAME": "BRUCKMANN",
      "IDNUMBER": "87356782"
    },
    {
      "id": 12,
      "MIDDLENAME": "MELICENT",
      "MPOBOX": "4856",
      "MTOWN": "SAN VICENTE PACAYA",
      "POCODE": "05012",
      "RTELNO": "0736735724",
      "STARTUPDATE": "2014/11/13",
      "TAXPAYERSPIN": "R654882919",
      "FISRTNAME": "KATHI",
      "LASTNAME": "STRETTELL",
      "IDNUMBER": "87356731"
    }
  ],
  "companies": [
    {
      "id": 1,
      "company_name": "Oberbrunner Inc",
      "location": "8 Grasskamp Terrace",
      "category": "Kids",
      "registration_no": "U246681015",
      "phone_no": "365-455-8833",
      "email": "kstitle0@soup.io"
    },
    {
      "id": 2,
      "company_name": "Willms and Sons",
      "location": "7 Crowley Pass",
      "category": "Automotive",
      "registration_no": "F713327339",
      "phone_no": "618-946-9229",
      "email": "cmcaulay1@icq.com"
    },
    {
      "id": 3,
      "company_name": "Skiles Inc",
      "location": "091 Fallview Point",
      "category": "Books",
      "registration_no": "V328344969",
      "phone_no": "492-707-6601",
      "email": "pzipsell2@google.ru"
    },
    {
      "id": 4,
      "company_name": "Ullrich, Kub and Haley",
      "location": "38402 Pond Road",
      "category": "Beauty",
      "registration_no": "R656916677",
      "phone_no": "560-822-4967",
      "email": "vbailey3@shutterfly.com"
    },
    {
      "id": 5,
      "company_name": "Smitham LLC",
      "location": "67856 Dakota Alley",
      "category": "Garden",
      "registration_no": "R017947099",
      "phone_no": "874-694-9178",
      "email": "gstoyell4@ocn.ne.jp"
    },
    {
      "id": 6,
      "company_name": "Douglas-Nikolaus",
      "location": "1929 Memorial Pass",
      "category": "Electronics",
      "registration_no": "L895012197",
      "phone_no": "368-262-4253",
      "email": "lguille5@timesonline.co.uk"
    }
  ]
}